bibi/__init__.py
bibi/main.py
setbot_pop-0.0.1.dist-info/LICENSE
setbot_pop-0.0.1.dist-info/METADATA
setbot_pop-0.0.1.dist-info/WHEEL
setbot_pop-0.0.1.dist-info/top_level.txt
setbot_pop-0.0.1.dist-info/RECORD
